collective.volto.socialsettings-0.2.2-py3.11-nspkg.pth
collective/volto/socialsettings/__init__.py
collective/volto/socialsettings/configure.zcml
collective/volto/socialsettings/interfaces.py
collective/volto/socialsettings/permissions.zcml
collective/volto/socialsettings/setuphandlers.py
collective/volto/socialsettings/testing.py
collective/volto/socialsettings/upgrades.py
collective/volto/socialsettings/upgrades.zcml
collective/volto/socialsettings/browser/__init__.py
collective/volto/socialsettings/browser/configure.zcml
collective/volto/socialsettings/browser/controlpanel.py
collective/volto/socialsettings/locales/README.rst
collective/volto/socialsettings/locales/__init__.py
collective/volto/socialsettings/locales/collective.volto.socialsettings.pot
collective/volto/socialsettings/locales/update.py
collective/volto/socialsettings/locales/update.sh
collective/volto/socialsettings/locales/en/LC_MESSAGES/collective.volto.socialsettings.po
collective/volto/socialsettings/locales/es/LC_MESSAGES/collective.volto.socialsettings.po
collective/volto/socialsettings/locales/it/LC_MESSAGES/collective.volto.socialsettings.po
collective/volto/socialsettings/profiles/default/browserlayer.xml
collective/volto/socialsettings/profiles/default/catalog.xml
collective/volto/socialsettings/profiles/default/controlpanel.xml
collective/volto/socialsettings/profiles/default/metadata.xml
collective/volto/socialsettings/profiles/default/registry.xml
collective/volto/socialsettings/profiles/default/rolemap.xml
collective/volto/socialsettings/profiles/uninstall/browserlayer.xml
collective/volto/socialsettings/profiles/uninstall/controlpanel.xml
collective/volto/socialsettings/restapi/__init__.py
collective/volto/socialsettings/restapi/configure.zcml
collective/volto/socialsettings/restapi/services/__init__.py
collective/volto/socialsettings/restapi/services/configure.zcml
collective/volto/socialsettings/restapi/services/controlpanel.py
collective.volto.socialsettings-0.2.2.dist-info/LICENSE.GPL
collective.volto.socialsettings-0.2.2.dist-info/LICENSE.rst
collective.volto.socialsettings-0.2.2.dist-info/METADATA
collective.volto.socialsettings-0.2.2.dist-info/WHEEL
collective.volto.socialsettings-0.2.2.dist-info/entry_points.txt
collective.volto.socialsettings-0.2.2.dist-info/namespace_packages.txt
collective.volto.socialsettings-0.2.2.dist-info/top_level.txt
collective.volto.socialsettings-0.2.2.dist-info/RECORD
